Workbook

Sheet Page de garde
B2: HPSHOP
B4: Helpmeprocess — Commerce en ligne (COD) en Guinée
B6: BUSINESS PLAN
B7: Dossier de recherche de financement — Investisseurs & bailleurs de fonds
B9: Projet | C9: HPSHOP — Site e-commerce (Helpmeprocess)
B10: Porteur de projet | C10: Abdourahamane Cissé — XPROCESS
B11: Date | C11: Juin 2026
B12: Objet | C12: Recherche de financement pour le lancement et la structuration
B14: MODÈLE ÉCONOMIQUE EN UNE PHRASE
B15: Achat de produits tendance en Chine / Dubaï via AfriShop, revente en ligne sur HPSHOP (paiement à la livraison — COD), avec confirmation des commandes et livraison sous-traitées à Rapido sur Conakry et l'intérieur du pays.

Sheet Pourquoi investir
A1: POURQUOI INVESTIR DANS CE MODÈLE
A2: Argumentaire stratégique — product-market fit déjà démontré
B4: 1. Le COD (paiement à la livraison) — taillé pour le marché guinéen
B5: En Guinée, la bancarisation reste faible et la méfiance envers le paiement en ligne anticipé est forte. Le COD lève ce frein : le client ne paie qu'à la réception physique du produit. La confiance est instaurée par l'acte d'achat lui-même, ce qui débloque la conversion là où le prépaiement échoue. C'est le mode de paiement le plus adapté au contexte local et le socle de notre modèle.
B8: 2. L'intérêt du e-commerce en Guinée aujourd'hui
B9: Marché jeune et forte pénétration mobile : Facebook et Instagram servent de vitrine commerciale directe. Il n'existe pas encore d'acteur structuré sur nos catégories (auto/entretien, beauté, tech accessible, maison). L'opportunité : devenir un acteur de référence avant l'arrivée de concurrents plus importants et mieux capitalisés.
A12: PREUVE DE TRACTION — CHIFFRES DÉJÀ RÉALISÉS AVEC AFRISHOP
B13: 100% | C13: 45 | D13: 30 | E13: 29
B14: Taux de livraison historique | C14: Engine Protectant (unités vendues) | D14: Car Carbon Fiber Film 5D (unités) | E14: Crème Visage Kojic (unités)
B16: • Top produits déjà validés par la demande réelle : Engine Protectant (45), Car Carbon Fiber Film 5D (30), Crème Visage Kojic (29), Shilajit Soft Candy et Googles (26 chacun).
B18: • Couverture géographique déjà opérationnelle : Conakry (toutes communes) + intérieur du pays (Coyah, Kamsar, Boké, etc.).
B20: • Charges opérationnelles actuelles ≈ 61% du chiffre d'affaires — mentionné en toute transparence. C'est précisément ce que le nouveau modèle (site propre + catalogue optimisé + Rapido) vise à améliorer.
A23: CONCLUSION
B24: Le product-market fit est déjà démontré sur des produits similaires et la demande est confirmée. Ce business plan présente l'étape de structuration — site propre HPSHOP, catalogue élargi, partenariat logistique formalisé avec Rapido — pour passer d'un test informel à une activité e-commerce structurée, pilotable et finançable.

Sheet Hypotheses
A1: HYPOTHÈSES & TAUX DE CHANGE
A2: Cellules en BLEU = modifiables. Les calculs (en noir) se mettent à jour automatiquement.
A3: Paramètre | B3: Valeur | C3: Unité | D3: Source / Note
A4: TAUX DE CHANGE
A5: 1 FCFA en GNF | B5: 15.5 | C5: GNF | D5: Taux moyen marché, juin 2026
A6: 1 USD en GNF | B6: 8775 | C6: GNF | D6: Taux moyen marché, juin 2026
A7: COÛTS & PRIX PRODUITS
A9: Coût d'achat — bas de fourchette | B9: 2500 | C9: FCFA | D9: Hypothèse
A10: Coût d'achat — haut de fourchette | B10: 3500 | C10: FCFA | D10: Hypothèse
A11: Coût d'achat retenu (milieu de fourchette) | B11: =(B9+B10)/2 -> 3000 | C11: FCFA | D11: Calcul
A12: Coût d'achat retenu | B12: =B11*B5 -> 46500 | C12: GNF | D12: Calcul (× taux FCFA)
A13: Prix de vente — bas de fourchette | B13: 180000 | C13: GNF | D13: Prix marché Guinée, juin 2026
A14: Prix de vente — haut de fourchette | B14: 250000 | C14: GNF | D14: Prix marché Guinée, juin 2026
A15: Prix de vente retenu (milieu de fourchette) | B15: =(B13+B14)/2 -> 215000 | C15: GNF | D15: Calcul
A16: Prix de vente retenu — base des calculs | B16: =B15 -> 215000 | C16: GNF | D16: Calcul (déjà en GNF, sans conversion)
A17: LOGISTIQUE & ACQUISITION
A19: Coût Rapido par commande livrée | B19: 70000 | C19: GNF | D19: Valeur fixe — porteur de projet
A20: Budget pub Meta — bas | B20: 5 | C20: USD/jour | D20: Hypothèse
A21: Budget pub Meta — haut | B21: 10 | C21: USD/jour | D21: Hypothèse
A22: Budget pub Meta retenu (milieu) | B22: =(B20+B21)/2 -> 7.5 | C22: USD/jour | D22: Calcul
A23: Budget pub Meta retenu | B23: =B22*B6 -> 65812.5 | C23: GNF/jour | D23: Calcul (× taux USD)
A24: VOLUME & PERFORMANCE
A26: Objectif commandes confirmées / jour | B26: 30 | C26: cmd/jour | D26: Hypothèse modifiable
A27: Taux de livraison réussie (COD) | B27: 0.7 | C27: % | D27: Ajustable — toutes les commandes confirmées ne sont pas livrées
A28: Commandes livrées / jour | B28: =B26*B27 -> 21 | C28: cmd/jour | D28: Calcul
A29: Jours opérés / mois | B29: 30 | C29: jours | D29: Hypothèse
A30: MONTÉE EN CHARGE (RAMP-UP) — % de l'objectif atteint
A31: Mois 1 | B31: 0.5 | C31: % | D31: Hypothèse de démarrage progressif
A32: Mois 2 | B32: 0.75 | C32: %
A33: Mois 3 | B33: 1 | C33: %
A34: Mois 4 | B34: 1 | C34: %
A35: Mois 5 | B35: 1 | C35: %
A36: Mois 6 | B36: 1 | C36: %

Sheet Catalogue
A1: CATALOGUE PRODUITS
A2: Coût (FCFA) et prix de vente (GNF) en BLEU = modifiables par produit (défaut = milieu de fourchette). Marges calculées.
A3: Produit | B3: Catégorie | C3: Coût achat (FCFA) | D3: Coût achat (GNF) | E3: Prix vente (GNF) | F3: Marge brute (GNF) | G3: Marge %
A4: Engine Protectant | B4: AUTO / ENTRETIEN | C4: 3000 | D4: =C4*Hypotheses!$B$5 -> 46500 | E4: 215000 | F4: =E4-D4 -> 168500 | G4: =F4/E4 -> 0.78372093
A5: Car Carbon Fiber Film 5D Black | B5: AUTO / ENTRETIEN | C5: 3000 | D5: =C5*Hypotheses!$B$5 -> 46500 | E5: 215000 | F5: =E5-D5 -> 168500 | G5: =F5/E5 -> 0.78372093
A6: Crème d'entretien pour cuir | B6: AUTO / ENTRETIEN | C6: 3000 | D6: =C6*Hypotheses!$B$5 -> 46500 | E6: 215000 | F6: =E6-D6 -> 168500 | G6: =F6/E6 -> 0.78372093
A7: Crème Visage Kojic | B7: BEAUTÉ & BIEN-ÊTRE | C7: 3000 | D7: =C7*Hypotheses!$B$5 -> 46500 | E7: 215000 | F7: =E7-D7 -> 168500 | G7: =F7/E7 -> 0.78372093
A8: Shilajit Soft Candy | B8: BEAUTÉ & BIEN-ÊTRE | C8: 3000 | D8: =C8*Hypotheses!$B$5 -> 46500 | E8: 215000 | F8: =E8-D8 -> 168500 | G8: =F8/E8 -> 0.78372093
A9: Tooth Whitening Powder | B9: BEAUTÉ & BIEN-ÊTRE | C9: 3000 | D9: =C9*Hypotheses!$B$5 -> 46500 | E9: 215000 | F9: =E9-D9 -> 168500 | G9: =F9/E9 -> 0.78372093
A10: Electric Nail Clippers | B10: BEAUTÉ & BIEN-ÊTRE | C10: 3000 | D10: =C10*Hypotheses!$B$5 -> 46500 | E10: 215000 | F10: =E10-D10 -> 168500 | G10: =F10/E10 -> 0.78372093
A11: Masques de protection moto (Goggles) | B11: TECH & JEUNESSE | C11: 3000 | D11: =C11*Hypotheses!$B$5 -> 46500 | E11: 215000 | F11: =E11-D11 -> 168500 | G11: =F11/E11 -> 0.78372093
A12: FlexiMag 3-in-1 | B12: TECH & JEUNESSE | C12: 3000 | D12: =C12*Hypotheses!$B$5 -> 46500 | E12: 215000 | F12: =E12-D12 -> 168500 | G12: =F12/E12 -> 0.78372093
A13: Chargeur de secours / power bank | B13: TECH & JEUNESSE | C13: 3000 | D13: =C13*Hypotheses!$B$5 -> 46500 | E13: 215000 | F13: =E13-D13 -> 168500 | G13: =F13/E13 -> 0.78372093
A14: Pack Smartwatch + écouteurs (iRed Ultra) | B14: TECH & JEUNESSE | C14: 3000 | D14: =C14*Hypotheses!$B$5 -> 46500 | E14: 215000 | F14: =E14-D14 -> 168500 | G14: =F14/E14 -> 0.78372093
A15: Caméra surveillance IP ampoule 360° | B15: ÉLECTROMÉNAGER & MAISON | C15: 3000 | D15: =C15*Hypotheses!$B$5 -> 46500 | E15: 215000 | F15: =E15-D15 -> 168500 | G15: =F15/E15 -> 0.78372093
... A17: Kit santé (tensiomètre+glycémie+oxymètre) | B17: ÉLECTROMÉNAGER & MAISON | C17: 3000 | D17: =C17*Hypotheses!$B$5 -> 46500 | E17: 215000 | F17: =E17-D17 -> 168500 | G17: =F17/E17 -> 0.78372093
A18: MOYENNE CATALOGUE | C18: =AVERAGE(C4:C17) -> 3000 | D18: =AVERAGE(D4:D17) -> 46500 | E18: =AVERAGE(E4:E17) -> 215000 | F18: =AVERAGE(F4:F17) -> 168500 | G18: =F18/E18 -> 0.78372093

Sheet Couts par commande
A1: COÛTS PAR COMMANDE — RENTABILITÉ UNITAIRE
A2: Toutes les valeurs proviennent de l'onglet Hypothèses.
A3: A. POUR UNE COMMANDE LIVRÉE
A4: Poste | B4: Montant | C4: Note
A5: Prix de vente (moyen) | B5: =Hypotheses!$B$16 -> 215000 | C5: Catalogue — prix retenu
A6: (–) Coût d'achat produit | B6: =Hypotheses!$B$12 -> 46500 | C6: Coût rendu hors transport
A7: (–) Coût Rapido (confirmation + livraison) | B7: =Hypotheses!$B$19 -> 70000 | C7: 70 000 GNF — valeur fixe
A8: (–) Coût publicitaire alloué / commande livrée | B8: =Hypotheses!$B$23/Hypotheses!$B$28 -> 3133.9286 | C8: Budget pub jour ÷ commandes livrées/jour
A9: ► Marge nette par commande livrée | B9: =B5-B6-B7-B8 -> 95366.071 | C9: Calcul
A10: Marge nette (%) | B10: =B9/B5 -> 0.44356312 | C10: Calcul
A12: B. IMPACT DU TAUX DE LIVRAISON (par jour)
A13: Poste | B13: Montant | C13: Note
A14: Commandes confirmées / jour | B14: =Hypotheses!$B$26 -> 30
A15: Taux de livraison réussie | B15: =Hypotheses!$B$27 -> 0.7
A16: Commandes livrées / jour | B16: =Hypotheses!$B$28 -> 21
A17: Commandes confirmées non livrées / jour | B17: =B14-B16 -> 9 | C17: Perte sèche pub
A18: Chiffre d'affaires / jour | B18: =B16*B5 -> 4515000 | C18: Livrées × prix
A19: (–) Coût des produits / jour | B19: =B16*B6 -> 976500
A20: (–) Coût Rapido / jour | B20: =B16*B7 -> 1470000
A21: (–) Coût publicitaire / jour | B21: =Hypotheses!$B$23 -> 65812.5 | C21: Dépensé quel que soit le taux
A22: ► Marge nette / jour | B22: =B18-B19-B20-B21 -> 2002687.5 | C22: Calcul
A23: Perte pub sur commandes non livrées / jour | B23: =B17*(Hypotheses!$B$23/Hypotheses!$B$26) -> 19743.75 | C23: Budget pub gaspillé sur non-livrées

Sheet Budget Pub Meta
A1: BUDGET PUBLICITÉ META (Facebook / Instagram)
A3: Paramètre | B3: Valeur | C3: Unité
A4: Budget pub / jour (retenu) | B4: =Hypotheses!$B$22 -> 7.5 | C4: USD/jour
A5: Budget pub / jour (retenu) | B5: =Hypotheses!$B$23 -> 65812.5 | C5: GNF/jour
A6: Jours / mois | B6: =Hypotheses!$B$29 -> 30 | C6: jours
A7: Budget pub / mois | B7: =B4*B6 -> 225 | C7: USD/mois
A8: Budget pub / mois | B8: =B5*B6 -> 1974375 | C8: GNF/mois
A9: Commandes confirmées visées / jour | B9: =Hypotheses!$B$26 -> 30 | C9: cmd/jour
A10: Commandes confirmées visées / mois | B10: =B9*B6 -> 900 | C10: cmd/mois
A11: Commandes livrées / mois | B11: =Hypotheses!$B$28*B6 -> 630 | C11: cmd/mois
A12: Coût d'acquisition / commande confirmée | B12: =B5/B9 -> 2193.75 | C12: CPA confirmée
A13: Coût d'acquisition / commande livrée | B13: =B5/Hypotheses!$B$28 -> 3133.9286 | C13: CPA livrée
A15: SCÉNARIOS DE BUDGET
A16: Scénario | B16: USD / jour | C16: GNF / jour | D16: GNF / mois | E16: CPA confirmée
A17: Prudent | B17: 5 | C17: =B17*Hypotheses!$B$6 -> 43875 | D17: =C17*Hypotheses!$B$29 -> 1316250 | E17: =C17/Hypotheses!$B$26 -> 1462.5
A18: Retenu | B18: =Hypotheses!$B$22 -> 7.5 | C18: =B18*Hypotheses!$B$6 -> 65812.5 | D18: =C18*Hypotheses!$B$29 -> 1974375 | E18: =C18/Hypotheses!$B$26 -> 2193.75
A19: Agressif | B19: 10 | C19: =B19*Hypotheses!$B$6 -> 87750 | D19: =C19*Hypotheses!$B$29 -> 2632500 | E19: =C19/Hypotheses!$B$26 -> 2925
A21: Note : ces hypothèses s'appuient sur des tests publicitaires réels déjà menés par l'entreprise sur le marché guinéen — et non sur des moyennes Facebook Europe/USA, non pertinentes ici.

Sheet Mise en place site
A1: MISE EN PLACE DU SITE HPSHOP — CAPEX
A2: Montants en BLEU = estimations à valider avant envoi au bailleur.
A3: Poste | B3: Montant (GNF) | C3: Note / Statut
A4: Développement & personnalisation du site HPSHOP | B4: 5000000 | C4: Estimation à valider
A5: Design, branding & logo | B5: 1500000 | C5: Estimation à valider
A6: Intégration paiement / COD / formulaire de commande | B6: 1000000 | C6: Estimation à valider
A7: Photos & contenu produits | B7: 1000000 | C7: Estimation à valider
A8: Nom de domaine (1 an) | B8: 300000 | C8: Estimation à valider
A9: Hébergement (1 an) | B9: 1200000 | C9: Estimation à valider
A10: Frais ponctuels divers (configuration, tests) | B10: 500000 | C10: Estimation à valider
A11: TOTAL CAPEX SITE | B11: =SUM(B4:B10) -> 10500000
A13: COÛTS FIXES MENSUELS RÉCURRENTS
A14: Poste | B14: Montant (GNF) | C14: Note
A15: Maintenance & mises à jour du site / mois | B15: 500000 | C15: Estimation à valider
A16: Hébergement + domaine amortis / mois | B16: =(B8+B9)/12 -> 125000 | C16: Calcul (postes annuels ÷ 12)
A17: TOTAL COÛT FIXE MENSUEL | B17: =SUM(B15:B16) -> 625000

Sheet Approvisionnement
A1: APPROVISIONNEMENT / SUPPLY CHAIN
A2: Cellules en BLEU = à compléter / ajuster (transport, délais).
A3: Paramètre | B3: Valeur | C3: Unité | D3: Note
A4: Coût d'achat unitaire (Chine) | B4: =Hypotheses!$B$11 -> 3000 | C4: FCFA | D4: Hypothèses
A5: Coût d'achat unitaire (Chine) | B5: =Hypotheses!$B$12 -> 46500 | C5: GNF | D5: Hypothèses
A6: Frais transport & import Chine→Guinée | B6: 0.15 | C6: % | D6: ESTIMATION — à compléter (% du coût d'achat)
A7: Coût d'achat rendu Guinée / unité | B7: =B5*(1+B6) -> 53475 | C7: GNF | D7: Calcul
A8: VOLUME & STOCK
A9: Commandes confirmées / jour (plein régime) | B9: =Hypotheses!$B$26 -> 30 | C9: cmd/j | D9: Hypothèses
A10: Délai d'approvisionnement estimé | B10: 15 | C10: jours | D10: ESTIMATION — à compléter
A11: Coefficient de stock de sécurité | B11: 1.5 | C11: x | D11: ESTIMATION — marge de sécurité
A12: Stock de sécurité recommandé | B12: =B9*B10*B11 -> 675 | C12: unités | D12: Calcul (cmd/j × délai × coef)
A13: Volume mensuel livré (plein régime) | B13: =Hypotheses!$B$28*Hypotheses!$B$29 -> 630 | C13: unités | D13: Calcul
A14: Coût d'achat mensuel (rendu Guinée) | B14: =B13*B7 -> 33689250 | C14: GNF | D14: Calcul
A15: Valeur du stock de sécurité (stock initial) | B15: =B12*B7 -> 36095625 | C15: GNF | D15: Calcul — sert au plan de financement

Sheet Resultat 6 mois
A1: COMPTE DE RÉSULTAT PRÉVISIONNEL — 6 MOIS
A2: Montée en charge progressive (ramp-up) modifiable dans l'onglet Hypothèses (lignes Mois 1 à 6).
A3: Poste (GNF) | B3: Mois 1 | C3: Mois 2 | D3: Mois 3 | E3: Mois 4 | F3: Mois 5 | G3: Mois 6 | H3: Total 6 mois
A4: % de l'objectif (ramp-up) | B4: =Hypotheses!$B$31 -> 0.5 | C4: =Hypotheses!$B$32 -> 0.75 | D4: =Hypotheses!$B$33 -> 1 | E4: =Hypotheses!$B$34 -> 1 | F4: =Hypotheses!$B$35 -> 1 | G4: =Hypotheses!$B$36 -> 1
A5: Commandes confirmées / jour | B5: =Hypotheses!$B$26*B4 -> 15 | C5: =Hypotheses!$B$26*C4 -> 22.5 | D5: =Hypotheses!$B$26*D4 -> 30 | E5: =Hypotheses!$B$26*E4 -> 30 | F5: =Hypotheses!$B$26*F4 -> 30 | G5: =Hypotheses!$B$26*G4 -> 30
A6: Commandes confirmées / mois | B6: =B5*Hypotheses!$B$29 -> 450 | C6: =C5*Hypotheses!$B$29 -> 675 | D6: =D5*Hypotheses!$B$29 -> 900 | E6: =E5*Hypotheses!$B$29 -> 900 | F6: =F5*Hypotheses!$B$29 -> 900 | G6: =G5*Hypotheses!$B$29 -> 900 | H6: =SUM(B6:G6) -> 4725
A7: Commandes livrées / mois | B7: =B6*Hypotheses!$B$27 -> 315 | C7: =C6*Hypotheses!$B$27 -> 472.5 | D7: =D6*Hypotheses!$B$27 -> 630 | E7: =E6*Hypotheses!$B$27 -> 630 | F7: =F6*Hypotheses!$B$27 -> 630 | G7: =G6*Hypotheses!$B$27 -> 630 | H7: =SUM(B7:G7) -> 3307.5
A9: Chiffre d'affaires | B9: =B7*Hypotheses!$B$16 -> 67725000 | C9: =C7*Hypotheses!$B$16 -> 1.015875e+08 | D9: =D7*Hypotheses!$B$16 -> 135450000 | E9: =E7*Hypotheses!$B$16 -> 135450000 | F9: =F7*Hypotheses!$B$16 -> 135450000 | G9: =G7*Hypotheses!$B$16 -> 135450000 | H9: =SUM(B9:G9) -> 711112500
A10: (–) Coût des produits vendus | B10: =B7*Hypotheses!$B$12 -> 14647500 | C10: =C7*Hypotheses!$B$12 -> 21971250 | D10: =D7*Hypotheses!$B$12 -> 29295000 | E10: =E7*Hypotheses!$B$12 -> 29295000 | F10: =F7*Hypotheses!$B$12 -> 29295000 | G10: =G7*Hypotheses!$B$12 -> 29295000 | H10: =SUM(B10:G10) -> 153798750
A11: ► Marge brute | B11: =B9-B10 -> 53077500 | C11: =C9-C10 -> 79616250 | D11: =D9-D10 -> 106155000 | E11: =E9-E10 -> 106155000 | F11: =F9-F10 -> 106155000 | G11: =G9-G10 -> 106155000 | H11: =SUM(B11:G11) -> 557313750
A12: (–) Coûts Rapido | B12: =B7*Hypotheses!$B$19 -> 22050000 | C12: =C7*Hypotheses!$B$19 -> 33075000 | D12: =D7*Hypotheses!$B$19 -> 44100000 | E12: =E7*Hypotheses!$B$19 -> 44100000 | F12: =F7*Hypotheses!$B$19 -> 44100000 | G12: =G7*Hypotheses!$B$19 -> 44100000 | H12: =SUM(B12:G12) -> 231525000
A13: (–) Coûts publicitaires | B13: =Hypotheses!$B$23*Hypotheses!$B$29 -> 1974375 | C13: =Hypotheses!$B$23*Hypotheses!$B$29 -> 1974375 | D13: =Hypotheses!$B$23*Hypotheses!$B$29 -> 1974375 | E13: =Hypotheses!$B$23*Hypotheses!$B$29 -> 1974375 | F13: =Hypotheses!$B$23*Hypotheses!$B$29 -> 1974375 | G13: =Hypotheses!$B$23*Hypotheses!$B$29 -> 1974375 | H13: =SUM(B13:G13) -> 11846250
A14: (–) Coûts fixes (site) | B14: ='Mise en place site'!$B$17 -> 625000 | C14: ='Mise en place site'!$B$17 -> 625000 | D14: ='Mise en place site'!$B$17 -> 625000 | E14: ='Mise en place site'!$B$17 -> 625000 | F14: ='Mise en place site'!$B$17 -> 625000 | G14: ='Mise en place site'!$B$17 -> 625000 | H14: =SUM(B14:G14) -> 3750000
A15: ► Résultat net | B15: =B11-B12-B13-B14 -> 28428125 | C15: =C11-C12-C13-C14 -> 43941875 | D15: =D11-D12-D13-D14 -> 59455625 | E15: =E11-E12-E13-E14 -> 59455625 | F15: =F11-F12-F13-F14 -> 59455625 | G15: =G11-G12-G13-G14 -> 59455625 | H15: =SUM(B15:G15) -> 310192500
A16: Résultat net cumulé | B16: =B15 -> 28428125 | C16: =B16+C15 -> 72370000 | D16: =C16+D15 -> 1.3182562e+08 | E16: =D16+E15 -> 191281250 | F16: =E16+F15 -> 250736875 | G16: =F16+G15 -> 310192500 | H16: =G16 -> 310192500

Sheet Synthese Investisseur
A1: SYNTHÈSE POUR L'INVESTISSEUR
A3: RENTABILITÉ UNITAIRE & SEUIL DE RENTABILITÉ (BREAK-EVEN)
A4: Indicateur | B4: Valeur | C4: Unité | D4: Note
A5: Marge contributive / commande livrée | B5: =Hypotheses!$B$16-Hypotheses!$B$12-Hypotheses!$B$19 -> 98500 | C5: GNF | D5: Prix – achat – Rapido (avant pub & fixes)
A6: Marge nette / commande livrée | B6: ='Couts par commande'!$B$9 -> 95366.071 | C6: GNF | D6: Après pub allouée
A7: Charges fixes journalières (pub + site) | B7: =Hypotheses!$B$23+'Mise en place site'!$B$17/Hypotheses!$B$29 -> 86645.833 | C7: GNF/j | D7: À couvrir chaque jour
A8: Break-even — commandes livrées / jour | B8: =B7/B5 -> 0.87965313 | C8: cmd/j | D8: Charges fixes ÷ marge contributive
A9: Break-even — commandes confirmées / jour | B9: =B8/Hypotheses!$B$27 -> 1.2566473 | C9: cmd/j | D9: Livrées ÷ taux de livraison
A10: Objectif confirmées / jour (plein régime) | B10: =Hypotheses!$B$26 -> 30 | C10: cmd/j | D10: Pour comparaison
A11: Marge de sécurité vs objectif | B11: =Hypotheses!$B$26/B9-1 -> 22.873046 | C11: % | D11: Au-dessus du seuil
A13: PLAN DE FINANCEMENT — UTILISATION DES FONDS
A14: Poste | B14: Montant (GNF) | C14: % du total | D14: Note
A15: CAPEX — mise en place du site | B15: ='Mise en place site'!$B$11 -> 10500000 | C15: =B15/$B$19 -> 0.083390416 | D15: Investissement initial site
A16: Stock initial (stock de sécurité) | B16: =Approvisionnement!$B$15 -> 36095625 | C16: =B16/$B$19 -> 0.28666945 | D16: Approvisionnement
A17: Budget publicité (3 mois) | B17: ='Budget Pub Meta'!$B$8*3 -> 5923125 | C17: =B17/$B$19 -> 0.047041129 | D17: Amorçage acquisition
A18: Fonds de roulement (1 mois charges variables) | B18: =(Hypotheses!$B$28*Hypotheses!$B$29)*(Hypotheses!$B$12+Hypotheses!$B$19) -> 73395000 | C18: =B18/$B$19 -> 0.58289901 | D18: Produits + Rapido, 1 mois plein régime
A19: FINANCEMENT TOTAL DEMANDÉ | B19: =SUM(B15:B18) -> 125913750 | C19: =SUM(C15:C18) -> 1
A21: RETOUR SUR INVESTISSEMENT (6 MOIS)
A22: Indicateur | B22: Valeur | C22: Unité | D22: Note
A23: Résultat net cumulé sur 6 mois | B23: ='Resultat 6 mois'!$G$16 -> 310192500 | C23: GNF | D23: Onglet Résultat 6 mois
A24: Chiffre d'affaires cumulé 6 mois | B24: ='Resultat 6 mois'!$H$9 -> 711112500 | C24: GNF
A25: ROI sur 6 mois | B25: ='Resultat 6 mois'!$G$16/B19 -> 2.4635316 | C25: % | D25: Résultat cumulé ÷ financement
A26: Marge nette moyenne | B26: ='Resultat 6 mois'!$G$16/'Resultat 6 mois'!$H$9 -> 0.43620735 | C26: % | D26: Résultat ÷ CA
A28: PRINCIPAUX FACTEURS DE RISQUE
A29: • Taux de change FCFA/GNF et USD/GNF : une dépréciation du GNF renchérit les achats — sensibilité testable via l'onglet Hypothèses.
A30: • Taux de livraison Rapido (COD) : chaque point de taux de livraison perdu réduit directement le CA et gaspille du budget pub.
A31: • Saisonnalité & coût publicitaire : le CPA Meta peut augmenter ; le budget pub est la principale charge variable à piloter.
A32: • Approvisionnement : délais et frais de transport Chine→Guinée non encore confirmés (à valider avec le transitaire).
